autorpt/__init__.py
autorpt/autorpt.py
autorpt/common.py
autorpt-0.1.0.dist-info/licenses/LICENSE
autorpt-0.1.0.dist-info/METADATA
autorpt-0.1.0.dist-info/WHEEL
autorpt-0.1.0.dist-info/dependency_links.txt
autorpt-0.1.0.dist-info/entry_points.txt
autorpt-0.1.0.dist-info/top_level.txt
autorpt-0.1.0.dist-info/RECORD
